{
  "version": "1.0",
  "description": "数据敏感分级标签体系 - 4级分级标准",
  "reference": "参考国家数据安全分级分类相关标准",
  "levels": {
    "第1级/公开": {
      "level": 1,
      "name": "公开",
      "description": "可向公众公开的数据，泄露不会造成影响",
      "characteristics": [
        "可以在官方网站或公开渠道获取",
        "不涉及个人隐私或商业秘密",
        "数据本身不具有敏感性"
      ],
      "examples": [
        "product_name (产品名称)",
        "category (产品类别)",
        "description (公开描述)",
        "city (城市名称)"
      ],
      "protection_requirement": "无需特殊保护",
      "risk_level": "低",
      "typical_fields": [
        "名称标题类字段",
        "公开分类代码",
        "产品标识编码",
        "序号排序字段"
      ]
    },
    "第2级/内部": {
      "level": 2,
      "name": "内部",
      "description": "仅限内部人员访问，泄露会造成轻微影响",
      "characteristics": [
        "仅企业内部可访问",
        "泄露可能影响企业运营",
        "不宜向外部公开"
      ],
      "examples": [
        "internal_code (内部编码)",
        "employee_department (员工部门)",
        "order_details (订单详情)",
        "create_time (创建时间)"
      ],
      "protection_requirement": "基本访问控制",
      "risk_level": "中低",
      "typical_fields": [
        "描述文本字段",
        "地址位置字段",
        "计量数值字段",
        "时间标记字段",
        "状态枚举字段"
      ]
    },
    "第3级/敏感": {
      "level": 3,
      "name": "敏感",
      "description": "泄露会造成较大影响，需要保护",
      "characteristics": [
        "涉及个人敏感信息",
        "泄露可能损害个人权益",
        "需要采取加密等措施"
      ],
      "examples": [
        "phone (电话号码)",
        "email (邮箱地址)",
        "salary (薪资信息)",
        "education (教育背景)"
      ],
      "protection_requirement": "加密存储、访问审计",
      "risk_level": "中高",
      "typical_fields": [
        "人口统计特征字段",
        "教育背景字段",
        "职业信息字段",
        "计量数值(敏感)"
      ]
    },
    "第4级/机密": {
      "level": 4,
      "name": "机密",
      "description": "泄露会造成严重后果，严格保护",
      "characteristics": [
        "高度敏感的个人信息",
        "泄露可能导致重大损失",
        "需要最严格的保护措施"
      ],
      "examples": [
        "id_card (身份证号)",
        "bank_account (银行账号)",
        "password (密码)",
        "secret_key (密钥)"
      ],
      "protection_requirement": "端到端加密、多因素认证、严格审计",
      "risk_level": "高",
      "typical_fields": [
        "联系方式字段",
        "身份认证信息",
        "金融账户信息",
        "密钥证书信息"
      ]
    }
  },
  "flattened_grades": [
    "第1级/公开",
    "第2级/内部",
    "第3级/敏感",
    "第4级/机密"
  ],
  "classification_to_grade_mapping": {
    "ID类/主键ID": "第1级/公开",
    "结构类/分类代码": "第1级/公开",
    "结构类/产品代码": "第1级/公开",
    "结构类/企业代码": "第1级/公开",
    "结构类/标准代码": "第1级/公开",
    "属性类/名称标题": "第1级/公开",
    "属性类/类别标签": "第1级/公开",
    "属性类/描述文本": "第2级/内部",
    "属性类/技能标签": "第2级/内部",
    "属性类/地址位置": "第2级/内部",
    "度量类/计量数值": "第2级/内部",
    "度量类/计数统计": "第2级/内部",
    "度量类/比率比例": "第2级/内部",
    "度量类/时间度量": "第2级/内部",
    "度量类/序号排序": "第1级/公开",
    "身份类/人口统计": "第3级/敏感",
    "身份类/联系方式": "第4级/机密",
    "身份类/教育背景": "第3级/敏感",
    "身份类/职业信息": "第3级/敏感",
    "状态类/二元标志": "第2级/内部",
    "状态类/状态枚举": "第2级/内部",
    "状态类/时间标记": "第2级/内部",
    "扩展类/扩展代码": "第2级/内部",
    "扩展类/其他字段": "第1级/公开"
  },
  "stats": {
    "total_levels": 4,
    "level_summary": {
      "第1级/公开": {"count": 9, "risk": "低"},
      "第2级/内部": {"count": 10, "risk": "中低"},
      "第3级/敏感": {"count": 4, "risk": "中高"},
      "第4级/机密": {"count": 1, "risk": "高"}
    }
  }
}
